ted/__init__.py
ted/__main__.py
ted/cli.py
ted/editor.css
ted/editor.py
ted/tui.py
ted_editor-0.1.3.dist-info/licenses/LICENSE
ted_editor-0.1.3.dist-info/METADATA
ted_editor-0.1.3.dist-info/WHEEL
ted_editor-0.1.3.dist-info/entry_points.txt
ted_editor-0.1.3.dist-info/top_level.txt
ted_editor-0.1.3.dist-info/RECORD
