Metadata-Version: 2.4
Name: ted-editor
Version: 0.1.3
Summary: Terminal Text Editor with TUI
Home-page: https://github.com/James4Ever0/ted
Author: James Brown
Author-email: randomvoidmail@foxmail.com
Classifier: Programming Language :: Python :: 3
Classifier: License :: OSI Approved :: The Unlicense (Unlicense)
Classifier: Operating System :: OS Independent
Requires-Python: >=3.7
License-File: LICENSE
Requires-Dist: textual>=0.1.18
Provides-Extra: syntax
Requires-Dist: textual[syntax]; extra == "syntax"
Dynamic: author
Dynamic: author-email
Dynamic: classifier
Dynamic: description
Dynamic: description-content-type
Dynamic: home-page
Dynamic: license-file
Dynamic: provides-extra
Dynamic: requires-dist
Dynamic: requires-python
Dynamic: summary
